sqlite_rag/__init__.py
sqlite_rag/_version.py
sqlite_rag/chunker.py
sqlite_rag/cli.py
sqlite_rag/database.py
sqlite_rag/engine.py
sqlite_rag/extractor.py
sqlite_rag/formatters.py
sqlite_rag/logger.py
sqlite_rag/reader.py
sqlite_rag/repository.py
sqlite_rag/sentence_splitter.py
sqlite_rag/settings.py
sqlite_rag/sqliterag.py
sqlite_rag/extractors/__init__.py
sqlite_rag/extractors/base.py
sqlite_rag/extractors/frontmatter.py
sqlite_rag/models/chunk.py
sqlite_rag/models/document.py
sqlite_rag/models/document_result.py
sqlite_rag/models/sentence.py
sqlite_rag/models/sentence_result.py
sqlite_rag-0.1.4.dist-info/METADATA
sqlite_rag-0.1.4.dist-info/WHEEL
sqlite_rag-0.1.4.dist-info/entry_points.txt
sqlite_rag-0.1.4.dist-info/top_level.txt
sqlite_rag-0.1.4.dist-info/RECORD
