Metadata-Version: 2.4
Name: sqlite-rag
Version: 0.1.4
Summary: Hybird search with SQLite AI and SQLite Vector
Author: SQLite AI Team
Project-URL: Homepage, https://sqlite.ai
Project-URL: Repository, https://github.com/sqliteai/sqlite-rag
Project-URL: Issues, https://github.com/sqliteai/sqlite-rag/issues
Classifier: Programming Language :: Python :: 3.10
Classifier: Programming Language :: Python :: 3.11
Classifier: Programming Language :: Python :: 3.12
Classifier: Programming Language :: Python :: 3.13
Classifier: Operating System :: OS Independent
Requires-Python: >=3.10
Requires-Dist: typer
Requires-Dist: huggingface_hub[hf_transfer]
Requires-Dist: markitdown[docx]
Requires-Dist: markitdown[outlook]
Requires-Dist: markitdown[pdf]
Requires-Dist: markitdown[pptx]
Requires-Dist: markitdown[xls]
Requires-Dist: markitdown[xlsx]
Requires-Dist: python-frontmatter
Requires-Dist: prompt-toolkit
Requires-Dist: sqlite-ai
Requires-Dist: sqliteai-vector
Provides-Extra: dev
Requires-Dist: pytest; extra == "dev"
Requires-Dist: pytest-mock; extra == "dev"
Requires-Dist: pytest-cov; extra == "dev"
Requires-Dist: black; extra == "dev"
Requires-Dist: flake8; extra == "dev"
Requires-Dist: bandit; extra == "dev"
Requires-Dist: isort; extra == "dev"
Requires-Dist: pre-commit; extra == "dev"
Requires-Dist: pyarrow; extra == "dev"
Requires-Dist: pandas; extra == "dev"
Requires-Dist: psutil; extra == "dev"
Requires-Dist: twine; extra == "dev"
Requires-Dist: build; extra == "dev"
